himawari_api/__init__.py
himawari_api/_version.py
himawari_api/alias.py
himawari_api/checks.py
himawari_api/download.py
himawari_api/explore.py
himawari_api/filter.py
himawari_api/info.py
himawari_api/io.py
himawari_api/listing.py
himawari_api/query.py
himawari_api/search.py
himawari_api-0.0.2.dist-info/LICENSE
himawari_api-0.0.2.dist-info/METADATA
himawari_api-0.0.2.dist-info/WHEEL
himawari_api-0.0.2.dist-info/top_level.txt
himawari_api-0.0.2.dist-info/RECORD
