Metadata-Version: 2.1
Name: himawari-api
Version: 0.0.2
Summary: Python API for downloading and searching Himawari satellite data on local and cloud storage.
Author-email: Gionata Ghiggi <gionata.ghiggi@epfl.ch>
License: MIT License
Project-URL: Homepage, https://github.com/ghiggi/himawari_api
Project-URL: Source, https://github.com/ghiggi/himawari_api
Project-URL: Tracker, https://github.com/ghiggi/himawari_api/issues
Project-URL: Documentation, https://himawari_api.readthedocs.io
Project-URL: changelog, https://github.com/ghigg/himawari_api/CHANGELOG.md
Keywords: Himawari-8,Himawari-9,AHI,satellite,weather,meteorology,forecasting,EWS
Classifier: Development Status :: 2 - Pre-Alpha
Classifier: Intended Audience :: Science/Research
Classifier: Intended Audience :: Education
Classifier: License :: OSI Approved :: MIT License
Classifier: Natural Language :: English
Classifier: Operating System :: OS Independent
Classifier: Operating System :: Unix
Classifier: Operating System :: Microsoft
Classifier: Operating System :: MacOS
Classifier: Programming Language :: Python
Classifier: Programming Language :: Python :: 3
Classifier: Programming Language :: Python :: 3 :: Only
Classifier: Programming Language :: Python :: 3.7
Classifier: Programming Language :: Python :: 3.8
Classifier: Programming Language :: Python :: 3.9
Classifier: Programming Language :: Python :: 3.10
Classifier: Programming Language :: Python :: 3.11
Classifier: Topic :: Scientific/Engineering
Classifier: Topic :: Scientific/Engineering :: Atmospheric Science
Requires-Python: >=3.7
License-File: LICENSE
Requires-Dist: numpy
Requires-Dist: pandas
Requires-Dist: tqdm
Requires-Dist: trollsift
Requires-Dist: fsspec
Requires-Dist: s3fs
Provides-Extra: dev
Requires-Dist: pre-commit ; extra == 'dev'
Requires-Dist: black ; extra == 'dev'
Requires-Dist: ruff ; extra == 'dev'
Requires-Dist: pytest ; extra == 'dev'
Requires-Dist: pytest-cov ; extra == 'dev'
Requires-Dist: pip-tools ; extra == 'dev'
Requires-Dist: bumpver ; extra == 'dev'
Requires-Dist: twine ; extra == 'dev'
Requires-Dist: setuptools (>=61.0.0) ; extra == 'dev'
Requires-Dist: wheel ; extra == 'dev'
Requires-Dist: build ; extra == 'dev'
Requires-Dist: sphinx ; extra == 'dev'
Requires-Dist: sphinx-gallery ; extra == 'dev'
Requires-Dist: nbsphinx ; extra == 'dev'
Provides-Extra: doc
Requires-Dist: sphinx ; extra == 'doc'
Requires-Dist: sphinx-gallery ; extra == 'doc'
Requires-Dist: nbsphinx ; extra == 'doc'
Provides-Extra: full
Requires-Dist: satpy ; extra == 'full'
Requires-Dist: xarray ; extra == 'full'
Requires-Dist: netcdf4 ; extra == 'full'
Provides-Extra: tests
Requires-Dist: pre-commit ; extra == 'tests'
Requires-Dist: pytest ; extra == 'tests'
Requires-Dist: pytest-cov ; extra == 'tests'
